arpes/__init__.py
arpes/analysis/__init__.py
arpes/analysis/align.py
arpes/analysis/background.py
arpes/analysis/band_analysis.py
arpes/analysis/band_analysis_utils.py
arpes/analysis/decomposition.py
arpes/analysis/deconvolution.py
arpes/analysis/derivative.py
arpes/analysis/filters.py
arpes/analysis/gap.py
arpes/analysis/general.py
arpes/analysis/kfermi.py
arpes/analysis/mask.py
arpes/analysis/moire.py
arpes/analysis/path.py
arpes/analysis/pocket.py
arpes/analysis/resolution.py
arpes/analysis/sarpes.py
arpes/analysis/savitzky_golay.py
arpes/analysis/self_energy.py
arpes/analysis/shirley.py
arpes/analysis/statistics.py
arpes/analysis/tarpes.py
arpes/analysis/xps.py
arpes/bootstrap.py
arpes/config.py
arpes/constants.py
arpes/corrections/__init__.py
arpes/corrections/background.py
arpes/corrections/fermi_edge_corrections.py
arpes/deep_learning/__init__.py
arpes/deep_learning/formatters.py
arpes/deep_learning/interpret.py
arpes/deep_learning/io.py
arpes/deep_learning/models/__init__.py
arpes/deep_learning/models/regression.py
arpes/deep_learning/transforms.py
arpes/endstations/__init__.py
arpes/endstations/base.py
arpes/endstations/plugins/ALG_MC.py
arpes/endstations/plugins/HHG.py
arpes/endstations/plugins/MAESTRO.py
arpes/endstations/plugins/SPEEM.py
arpes/endstations/plugins/__init__.py
arpes/endstations/plugins/example_data.py
arpes/endstations/plugins/fallback.py
arpes/endstations/utilities/common.py
arpes/endstations/utilities/fits.py
arpes/endstations/utilities/hdf5.py
arpes/endstations/utilities/pxt.py
arpes/example_data/cut.fits
arpes/example_data/fermi_surface.nc
arpes/example_data/nano_xps.nc
arpes/example_data/photon_energy.nc
arpes/example_data/temperature_dependence.nc
arpes/exceptions.py
arpes/experiment/__init__.py
arpes/fits/__init__.py
arpes/fits/broadcast_common.py
arpes/fits/fit_models/__init__.py
arpes/fits/fit_models/backgrounds.py
arpes/fits/fit_models/decay.py
arpes/fits/fit_models/dirac.py
arpes/fits/fit_models/fermi_edge.py
arpes_lite-1.0.1.dist-info/licenses/AUTHORS.md
arpes_lite-1.0.1.dist-info/licenses/LICENSE
arpes_lite-1.0.1.dist-info/WHEEL
arpes_lite-1.0.1.dist-info/METADATA
arpes_lite-1.0.1.dist-info/RECORD
